{
  "meta": {
    "generado": "2026-04-21T12:02:43.529410",
    "periodo": "2025",
    "tabla": "V_MUERTES",
    "ventana": "30 días",
    "desde": "2026-03-22",
    "hasta": "2026-04-21",
    "label_periodo": "Últimos 30 días (22/03/2026 – 21/04/2026)",
    "filtro_dias": ">30 días de encierre"
  },
  "mortandad": {
    "muertes_30d": 20,
    "ingresos_30d": 698,
    "stock_haras_hoy": 7665,
    "denominador": 8363,
    "tasa_mensual_pct": 0.239,
    "formula": "tasa = muertes_30d / (ingresos_30d + stock_hoy)",
    "por_grupo": {
      "Vacas": {
        "muertes": 13,
        "ingresos": 178,
        "stock": 2040,
        "denominador": 2218,
        "tasa_mensual_pct": 0.586
      },
      "Machos": {
        "muertes": 5,
        "ingresos": 391,
        "stock": 4330,
        "denominador": 4721,
        "tasa_mensual_pct": 0.106
      },
      "Hembras": {
        "muertes": 2,
        "ingresos": 129,
        "stock": 1295,
        "denominador": 1424,
        "tasa_mensual_pct": 0.14
      }
    }
  },
  "detalle": {
    "total_muertes": 20,
    "por_categoria": {
      "VA": 13,
      "TM": 2,
      "VQ": 2,
      "NT": 2,
      "NV": 1
    },
    "por_grupo": {
      "Vacas": 13,
      "Machos": 5,
      "Hembras": 2
    }
  }
}