{
  "meta": {
    "generado": "2026-04-27T05:01:38.998871",
    "periodo": "2025",
    "tabla": "V_STOCK_HACIENDA",
    "registros": 9860,
    "columnas": [
      "ID_TRAZABILIDAD",
      "CANTIDAD",
      "HOTELERO",
      "TIPO_ACTIVIDAD",
      "NRO_TROPA",
      "FECHA_INGRESO",
      "CANTIDAD_TROPA",
      "LOCALIDAD",
      "PROVINCIA",
      "CONSIGNATARIO",
      "PROVEEDOR",
      "RAZA",
      "SEXO",
      "CATEGORIA",
      "CARAVANA_VISUAL",
      "RFID",
      "KG_INGRESO",
      "CONTROLA_MOV_TROPA",
      "NRO_CORRAL",
      "FECHA_ULTIMA_PESADA",
      "ULTIMA_PESADA",
      "DIAS_ENCIERRE",
      "PESO_PROYECTADO",
      "DIAS_PESADA_CONTROL",
      "ULTIMA_ADPV_REAL",
      "ULTIMA_RACION",
      "ULTIMA_FECHA_REPARTO",
      "PESO_GORDO",
      "GANANCIA_PARA_PROYECTAR",
      "ULTIMO_DIAGNOSTICO",
      "CANTIDAD_PROTOCOLOS_SANITARIOS",
      "TOTAL_KILOS_TC",
      "TOTAL_KILOS_MS",
      "TOTAL_COSTO_ALIMENTACION",
      "KG_COSTO_TC",
      "KG_COSTO_MS",
      "DIAS_ALIMENTADOS",
      "CABEZAS_DIARIAS_ALIMENTADAS",
      "FECHA_ACTUAL",
      "DIAS_EN_FEEDLOT",
      "CLASIFICACION",
      "NOMBRE_CORRAL",
      "ENGORDE_DIARIO_KG",
      "KG_ESTIMADO_HOY",
      "CATEGORIA_FINAL"
    ]
  },
  "kpis": {
    "total_cabezas": 9860,
    "total_kg_estimado_hoy": 4345463,
    "total_ton_estimado_hoy": 4345.46,
    "kg_promedio_estimado": 440.7,
    "dias_promedio_feedlot": 135.5,
    "total_establecimientos": 3,
    "total_propietarios": 5,
    "por_categoria": {
      "NT": {
        "cabezas": 1812.0,
        "kg_estimado": 721413,
        "ton_estimado": 721.41,
        "kg_promedio": 398.1
      },
      "TM": {
        "cabezas": 2604.0,
        "kg_estimado": 1040848,
        "ton_estimado": 1040.85,
        "kg_promedio": 399.7
      },
      "TH": {
        "cabezas": 1733.0,
        "kg_estimado": 614745,
        "ton_estimado": 614.75,
        "kg_promedio": 354.7
      },
      "VA": {
        "cabezas": 2078.0,
        "kg_estimado": 1183306,
        "ton_estimado": 1183.31,
        "kg_promedio": 569.4
      },
      "TO": {
        "cabezas": 47.0,
        "kg_estimado": 25913,
        "ton_estimado": 25.91,
        "kg_promedio": 551.3
      },
      "NV": {
        "cabezas": 1042.0,
        "kg_estimado": 526818,
        "ton_estimado": 526.82,
        "kg_promedio": 505.6
      },
      "VQ": {
        "cabezas": 544.0,
        "kg_estimado": 232421,
        "ton_estimado": 232.42,
        "kg_promedio": 427.2
      }
    },
    "por_propietario": {
      "RICARDO BAILO": {
        "cabezas": 259.0,
        "kg_estimado": 139294,
        "ton_estimado": 139.29,
        "kg_promedio": 537.8
      },
      "PEGSA": {
        "cabezas": 8650.0,
        "kg_estimado": 3863992,
        "ton_estimado": 3863.99,
        "kg_promedio": 446.7
      },
      "LAS TAPERAS": {
        "cabezas": 338.0,
        "kg_estimado": 158746,
        "ton_estimado": 158.75,
        "kg_promedio": 469.7
      },
      "DARWASH SA": {
        "cabezas": 81.0,
        "kg_estimado": 51841,
        "ton_estimado": 51.84,
        "kg_promedio": 640.0
      },
      "TERCIO BRAVO SAS": {
        "cabezas": 532.0,
        "kg_estimado": 131590,
        "ton_estimado": 131.59,
        "kg_promedio": 247.3
      }
    },
    "por_establecimiento": {
      "El Haras": {
        "cabezas": 7977.0,
        "kg_estimado": 3855478,
        "ton_estimado": 3855.48,
        "kg_promedio": 483.3
      },
      "El Descanso": {
        "cabezas": 1351.0,
        "kg_estimado": 358396,
        "ton_estimado": 358.4,
        "kg_promedio": 265.3
      },
      "La Panchita": {
        "cabezas": 532.0,
        "kg_estimado": 131590,
        "ton_estimado": 131.59,
        "kg_promedio": 247.3
      }
    },
    "por_clasificacion": {
      "Macho": {
        "cabezas": 5458.0,
        "kg_estimado": 2289078,
        "ton_estimado": 2289.08,
        "kg_promedio": 419.4
      },
      "Hembra": {
        "cabezas": 2277.0,
        "kg_estimado": 847166,
        "ton_estimado": 847.17,
        "kg_promedio": 372.1
      },
      "Vaca": {
        "cabezas": 2078.0,
        "kg_estimado": 1183306,
        "ton_estimado": 1183.31,
        "kg_promedio": 569.4
      },
      "Toro": {
        "cabezas": 47.0,
        "kg_estimado": 25913,
        "ton_estimado": 25.91,
        "kg_promedio": 551.3
      }
    },
    "por_categoria_final": {
      "novillo mayor a 550 kg": {
        "cabezas": 941.0,
        "kg_estimado": 575516,
        "ton_estimado": 575.52,
        "kg_promedio": 611.6
      },
      "novillito": {
        "cabezas": 1053.0,
        "kg_estimado": 319938,
        "ton_estimado": 319.94,
        "kg_promedio": 303.8
      },
      "ternera": {
        "cabezas": 357.0,
        "kg_estimado": 73940,
        "ton_estimado": 73.94,
        "kg_promedio": 207.1
      },
      "novillo": {
        "cabezas": 2874.0,
        "kg_estimado": 1269573,
        "ton_estimado": 1269.57,
        "kg_promedio": 441.7
      },
      "vaquillona": {
        "cabezas": 1920.0,
        "kg_estimado": 773226,
        "ton_estimado": 773.23,
        "kg_promedio": 402.7
      },
      "ternero": {
        "cabezas": 590.0,
        "kg_estimado": 124050,
        "ton_estimado": 124.05,
        "kg_promedio": 210.3
      },
      "vaca mayor a 650 kg": {
        "cabezas": 519.0,
        "kg_estimado": 337350,
        "ton_estimado": 337.35,
        "kg_promedio": 650.0
      },
      "toro": {
        "cabezas": 47.0,
        "kg_estimado": 25913,
        "ton_estimado": 25.91,
        "kg_promedio": 551.3
      },
      "vaca": {
        "cabezas": 1559.0,
        "kg_estimado": 845956,
        "ton_estimado": 845.96,
        "kg_promedio": 542.6
      }
    },
    "por_establecimiento_categoria": {
      "El Haras": {
        "novillo mayor a 550 kg": {
          "cabezas": 941.0,
          "kg_estimado": 575516.3999999984,
          "ton_estimado": 575.52,
          "kg_promedio": 611.6
        },
        "vaquillona": {
          "cabezas": 1366.0,
          "kg_estimado": 614005.7000000046,
          "ton_estimado": 614.01,
          "kg_promedio": 449.5
        },
        "vaca mayor a 650 kg": {
          "cabezas": 519.0,
          "kg_estimado": 337350.0,
          "ton_estimado": 337.35,
          "kg_promedio": 650.0
        },
        "toro": {
          "cabezas": 47.0,
          "kg_estimado": 25913.19999999998,
          "ton_estimado": 25.91,
          "kg_promedio": 551.3
        },
        "novillo": {
          "cabezas": 2725.0,
          "kg_estimado": 1213389.7999999733,
          "ton_estimado": 1213.39,
          "kg_promedio": 445.3
        },
        "vaca": {
          "cabezas": 1559.0,
          "kg_estimado": 845955.7000000007,
          "ton_estimado": 845.96,
          "kg_promedio": 542.6
        },
        "novillito": {
          "cabezas": 667.0,
          "kg_estimado": 210834.60000000027,
          "ton_estimado": 210.83,
          "kg_promedio": 316.1
        },
        "ternero": {
          "cabezas": 124.0,
          "kg_estimado": 25992.499999999927,
          "ton_estimado": 25.99,
          "kg_promedio": 209.6
        },
        "ternera": {
          "cabezas": 29.0,
          "kg_estimado": 6520.0,
          "ton_estimado": 6.52,
          "kg_promedio": 224.8
        }
      },
      "El Descanso": {
        "novillito": {
          "cabezas": 351.0,
          "kg_estimado": 99282.5,
          "ton_estimado": 99.28,
          "kg_promedio": 282.9
        },
        "ternera": {
          "cabezas": 263.0,
          "kg_estimado": 52861.5,
          "ton_estimado": 52.86,
          "kg_promedio": 201.0
        },
        "novillo": {
          "cabezas": 149.0,
          "kg_estimado": 56183.5,
          "ton_estimado": 56.18,
          "kg_promedio": 377.1
        },
        "ternero": {
          "cabezas": 228.0,
          "kg_estimado": 46013.5,
          "ton_estimado": 46.01,
          "kg_promedio": 201.8
        },
        "vaquillona": {
          "cabezas": 360.0,
          "kg_estimado": 104054.5,
          "ton_estimado": 104.05,
          "kg_promedio": 289.0
        }
      },
      "La Panchita": {
        "vaquillona": {
          "cabezas": 194.0,
          "kg_estimado": 55165.40000000019,
          "ton_estimado": 55.17,
          "kg_promedio": 284.4
        },
        "ternera": {
          "cabezas": 65.0,
          "kg_estimado": 14559.0,
          "ton_estimado": 14.56,
          "kg_promedio": 224.0
        },
        "ternero": {
          "cabezas": 238.0,
          "kg_estimado": 52044.0,
          "ton_estimado": 52.04,
          "kg_promedio": 218.7
        },
        "novillito": {
          "cabezas": 35.0,
          "kg_estimado": 9821.299999999997,
          "ton_estimado": 9.82,
          "kg_promedio": 280.6
        }
      }
    },
    "por_categoria_desglose": {
      "novillo mayor a 550 kg": {
        "por_establecimiento": {
          "El Haras": {
            "cabezas": 941.0,
            "kg_estimado": 575516.3999999984,
            "ton_estimado": 575.52,
            "kg_promedio": 611.6
          }
        },
        "por_propietario": {
          "RICARDO BAILO": {
            "cabezas": 118.0,
            "kg_estimado": 73728.19999999998,
            "ton_estimado": 73.73,
            "kg_promedio": 624.8
          },
          "LAS TAPERAS": {
            "cabezas": 77.0,
            "kg_estimado": 48563.0,
            "ton_estimado": 48.56,
            "kg_promedio": 630.7
          },
          "DARWASH SA": {
            "cabezas": 9.0,
            "kg_estimado": 5738.0,
            "ton_estimado": 5.74,
            "kg_promedio": 637.6
          },
          "PEGSA": {
            "cabezas": 737.0,
            "kg_estimado": 447487.20000000147,
            "ton_estimado": 447.49,
            "kg_promedio": 607.2
          }
        }
      },
      "novillito": {
        "por_establecimiento": {
          "El Descanso": {
            "cabezas": 351.0,
            "kg_estimado": 99282.5,
            "ton_estimado": 99.28,
            "kg_promedio": 282.9
          },
          "La Panchita": {
            "cabezas": 35.0,
            "kg_estimado": 9821.299999999997,
            "ton_estimado": 9.82,
            "kg_promedio": 280.6
          },
          "El Haras": {
            "cabezas": 667.0,
            "kg_estimado": 210834.60000000027,
            "ton_estimado": 210.83,
            "kg_promedio": 316.1
          }
        },
        "por_propietario": {
          "PEGSA": {
            "cabezas": 1000.0,
            "kg_estimado": 304429.2000000008,
            "ton_estimado": 304.43,
            "kg_promedio": 304.4
          },
          "TERCIO BRAVO SAS": {
            "cabezas": 35.0,
            "kg_estimado": 9821.299999999997,
            "ton_estimado": 9.82,
            "kg_promedio": 280.6
          },
          "LAS TAPERAS": {
            "cabezas": 17.0,
            "kg_estimado": 5344.5,
            "ton_estimado": 5.34,
            "kg_promedio": 314.4
          },
          "RICARDO BAILO": {
            "cabezas": 1.0,
            "kg_estimado": 343.4,
            "ton_estimado": 0.34,
            "kg_promedio": 343.4
          }
        }
      },
      "ternera": {
        "por_establecimiento": {
          "El Descanso": {
            "cabezas": 263.0,
            "kg_estimado": 52861.5,
            "ton_estimado": 52.86,
            "kg_promedio": 201.0
          },
          "La Panchita": {
            "cabezas": 65.0,
            "kg_estimado": 14559.0,
            "ton_estimado": 14.56,
            "kg_promedio": 224.0
          },
          "El Haras": {
            "cabezas": 29.0,
            "kg_estimado": 6520.0,
            "ton_estimado": 6.52,
            "kg_promedio": 224.8
          }
        },
        "por_propietario": {
          "PEGSA": {
            "cabezas": 271.0,
            "kg_estimado": 54605.99999999997,
            "ton_estimado": 54.61,
            "kg_promedio": 201.5
          },
          "TERCIO BRAVO SAS": {
            "cabezas": 65.0,
            "kg_estimado": 14559.0,
            "ton_estimado": 14.56,
            "kg_promedio": 224.0
          },
          "LAS TAPERAS": {
            "cabezas": 21.0,
            "kg_estimado": 4775.5,
            "ton_estimado": 4.78,
            "kg_promedio": 227.4
          }
        }
      },
      "novillo": {
        "por_establecimiento": {
          "El Descanso": {
            "cabezas": 149.0,
            "kg_estimado": 56183.5,
            "ton_estimado": 56.18,
            "kg_promedio": 377.1
          },
          "El Haras": {
            "cabezas": 2725.0,
            "kg_estimado": 1213389.7999999733,
            "ton_estimado": 1213.39,
            "kg_promedio": 445.3
          }
        },
        "por_propietario": {
          "PEGSA": {
            "cabezas": 2647.0,
            "kg_estimado": 1167409.1999999825,
            "ton_estimado": 1167.41,
            "kg_promedio": 441.0
          },
          "RICARDO BAILO": {
            "cabezas": 140.0,
            "kg_estimado": 65222.50000000007,
            "ton_estimado": 65.22,
            "kg_promedio": 465.9
          },
          "LAS TAPERAS": {
            "cabezas": 87.0,
            "kg_estimado": 36941.599999999984,
            "ton_estimado": 36.94,
            "kg_promedio": 424.6
          }
        }
      },
      "vaquillona": {
        "por_establecimiento": {
          "El Haras": {
            "cabezas": 1366.0,
            "kg_estimado": 614005.7000000046,
            "ton_estimado": 614.01,
            "kg_promedio": 449.5
          },
          "El Descanso": {
            "cabezas": 360.0,
            "kg_estimado": 104054.5,
            "ton_estimado": 104.05,
            "kg_promedio": 289.0
          },
          "La Panchita": {
            "cabezas": 194.0,
            "kg_estimado": 55165.40000000019,
            "ton_estimado": 55.17,
            "kg_promedio": 284.4
          }
        },
        "por_propietario": {
          "LAS TAPERAS": {
            "cabezas": 98.0,
            "kg_estimado": 49945.10000000002,
            "ton_estimado": 49.95,
            "kg_promedio": 509.6
          },
          "PEGSA": {
            "cabezas": 1619.0,
            "kg_estimado": 662535.1000000038,
            "ton_estimado": 662.54,
            "kg_promedio": 409.2
          },
          "DARWASH SA": {
            "cabezas": 9.0,
            "kg_estimado": 5580.0,
            "ton_estimado": 5.58,
            "kg_promedio": 620.0
          },
          "TERCIO BRAVO SAS": {
            "cabezas": 194.0,
            "kg_estimado": 55165.40000000019,
            "ton_estimado": 55.17,
            "kg_promedio": 284.4
          }
        }
      },
      "ternero": {
        "por_establecimiento": {
          "El Descanso": {
            "cabezas": 228.0,
            "kg_estimado": 46013.5,
            "ton_estimado": 46.01,
            "kg_promedio": 201.8
          },
          "La Panchita": {
            "cabezas": 238.0,
            "kg_estimado": 52044.0,
            "ton_estimado": 52.04,
            "kg_promedio": 218.7
          },
          "El Haras": {
            "cabezas": 124.0,
            "kg_estimado": 25992.499999999927,
            "ton_estimado": 25.99,
            "kg_promedio": 209.6
          }
        },
        "por_propietario": {
          "PEGSA": {
            "cabezas": 325.0,
            "kg_estimado": 65979.49999999997,
            "ton_estimado": 65.98,
            "kg_promedio": 203.0
          },
          "TERCIO BRAVO SAS": {
            "cabezas": 238.0,
            "kg_estimado": 52044.0,
            "ton_estimado": 52.04,
            "kg_promedio": 218.7
          },
          "LAS TAPERAS": {
            "cabezas": 27.0,
            "kg_estimado": 6026.5,
            "ton_estimado": 6.03,
            "kg_promedio": 223.2
          }
        }
      },
      "vaca mayor a 650 kg": {
        "por_establecimiento": {
          "El Haras": {
            "cabezas": 519.0,
            "kg_estimado": 337350.0,
            "ton_estimado": 337.35,
            "kg_promedio": 650.0
          }
        },
        "por_propietario": {
          "PEGSA": {
            "cabezas": 463.0,
            "kg_estimado": 300950.0,
            "ton_estimado": 300.95,
            "kg_promedio": 650.0
          },
          "LAS TAPERAS": {
            "cabezas": 11.0,
            "kg_estimado": 7150.0,
            "ton_estimado": 7.15,
            "kg_promedio": 650.0
          },
          "DARWASH SA": {
            "cabezas": 45.0,
            "kg_estimado": 29250.0,
            "ton_estimado": 29.25,
            "kg_promedio": 650.0
          }
        }
      },
      "toro": {
        "por_establecimiento": {
          "El Haras": {
            "cabezas": 47.0,
            "kg_estimado": 25913.19999999998,
            "ton_estimado": 25.91,
            "kg_promedio": 551.3
          }
        },
        "por_propietario": {
          "PEGSA": {
            "cabezas": 47.0,
            "kg_estimado": 25913.19999999998,
            "ton_estimado": 25.91,
            "kg_promedio": 551.3
          }
        }
      },
      "vaca": {
        "por_establecimiento": {
          "El Haras": {
            "cabezas": 1559.0,
            "kg_estimado": 845955.7000000007,
            "ton_estimado": 845.96,
            "kg_promedio": 542.6
          }
        },
        "por_propietario": {
          "PEGSA": {
            "cabezas": 1541.0,
            "kg_estimado": 834682.7000000007,
            "ton_estimado": 834.68,
            "kg_promedio": 541.7
          },
          "DARWASH SA": {
            "cabezas": 18.0,
            "kg_estimado": 11273.0,
            "ton_estimado": 11.27,
            "kg_promedio": 626.3
          }
        }
      }
    }
  }
}